{"nodes": [{"id": "testimonials_section", "label": "Testimonials Section", "file_type": "code", "source_file": "src/components/Testimonials.astro", "source_location": null, "source_url": null, "captured_at": null, "author": null, "contributor": null}, {"id": "testimonials_data_array", "label": "Testimonials Data Array", "file_type": "code", "source_file": "src/components/Testimonials.astro", "source_location": "lines 2-27", "source_url": null, "captured_at": null, "author": null, "contributor": null}], "edges": [{"source": "testimonials_section", "target": "testimonials_data_array", "relation": "references", "confidence": "EXTRACTED", "confidence_score": 1.0, "source_file": "src/components/Testimonials.astro", "source_location": "lines 37-46", "weight": 1.0}, {"source": "testimonials_section", "target": "global_css_testimonials_styles", "relation": "implements", "confidence": "EXTRACTED", "confidence_score": 1.0, "source_file": "src/components/Testimonials.astro", "source_location": null, "weight": 1.0}], "hyperedges": []}